jms_client/__init__.py
jms_client/authentication.py
jms_client/client.py
jms_client/const.py
jms_client/exceptions.py
jms_client/session.py
jms_client/utils/__init__.py
jms_client/utils/common.py
jms_client/utils/logger.py
jms_client/utils/version.py
jms_client/v1/__init__.py
jms_client/v1/client.py
jms_client/v1/models/__init__.py
jms_client/v1/models/instance/__init__.py
jms_client/v1/models/instance/accounts/__init__.py
jms_client/v1/models/instance/accounts/account_templates.py
jms_client/v1/models/instance/accounts/accounts.py
jms_client/v1/models/instance/assets/__init__.py
jms_client/v1/models/instance/assets/assets.py
jms_client/v1/models/instance/assets/domains.py
jms_client/v1/models/instance/assets/nodes.py
jms_client/v1/models/instance/assets/platforms.py
jms_client/v1/models/instance/audits/__init__.py
jms_client/v1/models/instance/audits/activities.py
jms_client/v1/models/instance/audits/change_password_logs.py
jms_client/v1/models/instance/audits/commands.py
jms_client/v1/models/instance/audits/ftp_logs.py
jms_client/v1/models/instance/audits/job_logs.py
jms_client/v1/models/instance/audits/login_logs.py
jms_client/v1/models/instance/audits/operate_logs.py
jms_client/v1/models/instance/audits/sessions.py
jms_client/v1/models/instance/audits/user_sessions.py
jms_client/v1/models/instance/common.py
jms_client/v1/models/instance/general.py
jms_client/v1/models/instance/labels/__init__.py
jms_client/v1/models/instance/labels/labels.py
jms_client/v1/models/instance/organizations/__init__.py
jms_client/v1/models/instance/organizations/organizations.py
jms_client/v1/models/instance/permissions/__init__.py
jms_client/v1/models/instance/permissions/asset_login_acl.py
jms_client/v1/models/instance/permissions/command_acls.py
jms_client/v1/models/instance/permissions/connect_method_acls.py
jms_client/v1/models/instance/permissions/permissions.py
jms_client/v1/models/instance/permissions/user_login_acl.py
jms_client/v1/models/instance/settings/__init__.py
jumpserver_sdk-0.9.0.dist-info/METADATA
jumpserver_sdk-0.9.0.dist-info/WHEEL
jumpserver_sdk-0.9.0.dist-info/RECORD
