Metadata-Version: 2.1
Name: jumpserver-sdk
Version: 0.9.0
Summary: JumpServer Python SDK
Author: jiangweidong
Author-email: 1053570670@qq.com
Requires-Python: >=3.8,<4.0
Classifier: Programming Language :: Python :: 3
Classifier: Programming Language :: Python :: 3.8
Classifier: Programming Language :: Python :: 3.9
Classifier: Programming Language :: Python :: 3.10
Classifier: Programming Language :: Python :: 3.11
Classifier: Programming Language :: Python :: 3.12
Classifier: Programming Language :: Python :: 3.13
Requires-Dist: httpsig (>=1.3.0,<2.0.0)
Requires-Dist: requests (>=2.32.3,<3.0.0)
